taxonomy_utils/__init__.py
taxonomy_utils/taxonomy_utils.py
taxonomy_utils-0.1.2.dist-info/AUTHORS.rst
taxonomy_utils-0.1.2.dist-info/LICENSE
taxonomy_utils-0.1.2.dist-info/METADATA
taxonomy_utils-0.1.2.dist-info/WHEEL
taxonomy_utils-0.1.2.dist-info/top_level.txt
taxonomy_utils-0.1.2.dist-info/RECORD
