Metadata-Version: 2.1
Name: taxonomy-utils
Version: 0.1.2
Summary: Python package to handle taxonomy categories, subcategories and labeling. Useful to work with hf datasets.
Home-page: https://gitlab.expert.ai/gblanco/taxonomy_utils
Author: Guillermo E. Blanco
Author-email: gblanco@expert.ai
License: MIT license
Keywords: taxonomy_utils
Platform: UNKNOWN
Classifier: Development Status :: 2 - Pre-Alpha
Classifier: Intended Audience :: Developers
Classifier: License :: OSI Approved :: MIT License
Classifier: Natural Language :: English
Classifier: Programming Language :: Python :: 3
Classifier: Programming Language :: Python :: 3.6
Classifier: Programming Language :: Python :: 3.7
Classifier: Programming Language :: Python :: 3.8
Requires-Python: >=3.6
License-File: LICENSE
License-File: AUTHORS.rst
